fextapi/__init__.py
fextapi/cli/__init__.py
fextapi/cli/init.py
fextapi/cli/main.py
fextapi/cli/run.py
fextapi/cli/templates/README.md.template
fextapi/cli/templates/main.py.template
fextapi/cli/templates/pyproject.toml.template
fextapi/cli/templates/route.py.template
fextapi/router/__init__.py
fextapi/router/loader.py
fextapi/router/registry.py
fextapi/router/scanner.py
fextapi/utils/__init__.py
fextapi/utils/path.py
fextapi-0.1.12.dist-info/METADATA
fextapi-0.1.12.dist-info/WHEEL
fextapi-0.1.12.dist-info/entry_points.txt
fextapi-0.1.12.dist-info/licenses/LICENSE
fextapi-0.1.12.dist-info/RECORD
