Metadata-Version: 2.4
Name: fextapi
Version: 0.1.12
Summary: File-system based routing for FastAPI
Project-URL: Homepage, https://github.com/johnnydddd/fextapi
Project-URL: Repository, https://github.com/johnnydddd/fextapi
Project-URL: Documentation, https://github.com/johnnydddd/fextapi#readme
Author-email: fextapi Team <sk20220@gmail.com>
License-File: LICENSE
Keywords: api,fastapi,framework,routing
Classifier: Development Status :: 3 - Alpha
Classifier: Framework :: FastAPI
Classifier: Intended Audience :: Developers
Classifier: Programming Language :: Python :: 3
Classifier: Programming Language :: Python :: 3.13
Requires-Python: >=3.13
Requires-Dist: build>=1.3.0
Requires-Dist: fastapi>=0.100.0
Requires-Dist: twine>=6.2.0
Requires-Dist: uvicorn[standard]>=0.20.0
